static_tl/__init__.py
static_tl/config.py
static_tl/gen.py
static_tl/gen_html.py
static_tl/get.py
static_tl/get_tweets.py
static_tl/main.py
static_tl/search.py
static_tl/storage.py
static_tl/static/feed-icon.png
static_tl/templates/by_month.html
static_tl/templates/feed-icon.png
static_tl/templates/footer.html
static_tl/templates/index.html
static_tl/templates/search.html
static_tl/templates/search_results.html
static_tl/templates/user_index.html
static_tl-0.5.3.dist-info/DESCRIPTION.rst
static_tl-0.5.3.dist-info/METADATA
static_tl-0.5.3.dist-info/RECORD
static_tl-0.5.3.dist-info/WHEEL
static_tl-0.5.3.dist-info/entry_points.txt
static_tl-0.5.3.dist-info/metadata.json
static_tl-0.5.3.dist-info/top_level.txt
