Metadata-Version: 2.0
Name: static-tl
Version: 0.5.3
Summary: Generate a static HTML website from your twitter time line
Home-page: https://github.com/dmerejkowsy/static_tl
Author: Dimitri Merejkowsky
Author-email: d.merej@gmail.com
License: BSD
Platform: UNKNOWN
Classifier: Environment :: Console
Classifier: License :: OSI Approved :: BSD License
Classifier: Programming Language :: Python :: 3 :: Only
Requires-Dist: arrow
Requires-Dist: feedgenerator
Requires-Dist: flask
Requires-Dist: jinja2
Requires-Dist: toml
Requires-Dist: twitter
